agentweave/__init__.py
agentweave/cli/__init__.py
agentweave/cli/main.py
agentweave/templates/basic/README.md
agentweave/templates/basic/agentweave.yaml
agentweave/templates/basic/check_tools.py
agentweave/templates/basic/requirements.txt
agentweave/templates/basic/schema.yaml
agentweave/templates/basic/setup.py
agentweave/templates/basic/agents/__init__.py
agentweave/templates/basic/agents/agent.py
agentweave/templates/basic/agents/document_processor.py
agentweave/templates/basic/backend/__init__.py
agentweave/templates/basic/backend/main.py
agentweave/templates/basic/backend/routers/__init__.py
agentweave/templates/basic/backend/routers/agent.py
agentweave/templates/basic/backend/routers/documents.py
agentweave/templates/basic/backend/routers/tools.py
agentweave/templates/basic/backend/utils/config.py
agentweave/templates/basic/backend/vector_store/chroma.sqlite3
agentweave/templates/basic/documents/faiss_index/index.faiss
agentweave/templates/basic/documents/faiss_index/index.pkl
agentweave/templates/basic/frontend/components.json
agentweave/templates/basic/frontend/next-env.d.ts
agentweave/templates/basic/frontend/next.config.js
agentweave/templates/basic/frontend/package-lock.json
agentweave/templates/basic/frontend/package.json
agentweave/templates/basic/frontend/postcss.config.js
agentweave/templates/basic/frontend/tailwind.config.js
agentweave/templates/basic/frontend/tsconfig.json
agentweave/templates/basic/frontend/src/app/globals.css
agentweave/templates/basic/frontend/src/app/layout.tsx
agentweave/templates/basic/frontend/src/app/page.tsx
agentweave/templates/basic/frontend/src/app/providers.tsx
agentweave/templates/basic/frontend/src/components/ChatMessage.tsx
agentweave/templates/basic/frontend/src/components/DocumentViewer.tsx
agentweave/templates/basic/frontend/src/components/Footer.tsx
agentweave/templates/basic/frontend/src/components/Header.tsx
agentweave/templates/basic/frontend/src/components/Resizable.tsx
agentweave-0.0.6.dist-info/licenses/LICENSE
agentweave-0.0.6.dist-info/METADATA
agentweave-0.0.6.dist-info/WHEEL
agentweave-0.0.6.dist-info/entry_points.txt
agentweave-0.0.6.dist-info/top_level.txt
agentweave-0.0.6.dist-info/RECORD
