Metadata-Version: 2.4
Name: agentweave
Version: 0.0.6
Summary: CLI tool for initializing and managing AI agent projects based on LangGraph
Author: AgentWeave Team
License: MIT
Classifier: Development Status :: 3 - Alpha
Classifier: Intended Audience :: Developers
Classifier: License :: OSI Approved :: MIT License
Classifier: Programming Language :: Python :: 3
Classifier: Programming Language :: Python :: 3.9
Classifier: Programming Language :: Python :: 3.10
Classifier: Programming Language :: Python :: 3.11
Requires-Python: >=3.9
License-File: LICENSE
Requires-Dist: click>=8.1.3
Requires-Dist: rich>=12.0.0
Requires-Dist: pyyaml>=6.0
Requires-Dist: jinja2>=3.1.2
Requires-Dist: langgraph>=0.0.30
Requires-Dist: fastapi>=0.100.0
Requires-Dist: uvicorn>=0.22.0
Requires-Dist: typer>=0.9.0
Requires-Dist: psutil>=6.0.0
Provides-Extra: dev
Requires-Dist: pytest>=7.0.0; extra == "dev"
Requires-Dist: ruff==0.11.9; extra == "dev"
Dynamic: license-file
